derivehelper/__init__.py
derivehelper/derivehelper.py
derivehelper-0.5.dist-info/METADATA
derivehelper-0.5.dist-info/WHEEL
derivehelper-0.5.dist-info/top_level.txt
derivehelper-0.5.dist-info/RECORD
