Metadata-Version: 2.1
Name: derivehelper
Version: 0.5
Summary: DeriveHelper Script
Home-page: UNKNOWN
Author: m-benja
Author-email: <m.benja@protonmail.ch>
License: UNKNOWN
Keywords: python,cryptography
Platform: UNKNOWN
Classifier: Development Status :: 5 - Production/Stable
Classifier: Intended Audience :: Developers
Classifier: Programming Language :: Python :: 3
Classifier: Operating System :: Unix
Classifier: Operating System :: MacOS :: MacOS X
Classifier: Operating System :: Microsoft :: Windows
Requires-Dist: argon2-cffi
Requires-Dist: cryptography
Requires-Dist: bcrypt
Requires-Dist: pynacl
Requires-Dist: passlib
